LICENSE
README.md
setup.cfg
setup.py
socrata_dump/__init__.py
socrata_dump.egg-info/PKG-INFO
socrata_dump.egg-info/SOURCES.txt
socrata_dump.egg-info/dependency_links.txt
socrata_dump.egg-info/entry_points.txt
socrata_dump.egg-info/requires.txt
socrata_dump.egg-info/top_level.txt