Metadata-Version: 2.1
Name: socrata-dump
Version: 0.1.2
Summary: Dump Socrata Instance into a Folder, including both Metadata and Data
Home-page: https://github.com/officeofperformancemanagement/socrata-dump
Download-URL: https://github.com/officeofperformancemanagement/socrata-dump/tarball/download
Author: Daniel J. Dufour
Author-email: daniel.j.dufour@gmail.com
Keywords: data,python,socrata
Classifier: Development Status :: 4 - Beta
Classifier: Programming Language :: Python :: 3
Classifier: License :: CC0 1.0 Universal (CC0 1.0) Public Domain Dedication
Classifier: Operating System :: OS Independent
License-File: LICENSE
Requires-Dist: requests
